targeted-0.0.35.dist-info/RECORD
targeted-0.0.35.dist-info/LICENSE
targeted-0.0.35.dist-info/WHEEL
targeted-0.0.35.dist-info/top_level.txt
targeted-0.0.35.dist-info/METADATA
targeted-0.0.35.data/scripts/test_targeted
targeted/libarmadillo.11.dylib
targeted/libarmadillo.dylib
targeted/libarmadillo.11.4.1.dylib
targeted/riskreg.py
targeted/__init__.py
targeted/__targeted_c__.cpython-312-darwin.so
targeted/__about__.py
targeted/__utils__.py
targeted/__main__.py
targeted/data.py
targeted/formula/riskreg.py
targeted/formula/__init__.py
targeted/data/d.csv.gz
targeted/data/surgunit.csv.gz
