Metadata-Version: 2.1
Name: targeted
Version: 0.0.35
Summary: Python package for targeted inference.
Home-page: https://targetlib.org/python/
Author: Klaus Kähler Holst
Author-email: klaus.holst@maersk.com
License: Apache Software License
Classifier: Programming Language :: Python :: 3
Classifier: Programming Language :: C++
Classifier: Intended Audience :: Science/Research
Classifier: Topic :: Scientific/Engineering :: Mathematics
Classifier: License :: OSI Approved :: Apache Software License
Classifier: Operating System :: OS Independent
License-File: LICENSE
